alpha_galaxy/__init__.py
alpha_galaxy-0.1.0.dist-info/LICENSE
alpha_galaxy-0.1.0.dist-info/WHEEL
alpha_galaxy-0.1.0.dist-info/METADATA
alpha_galaxy-0.1.0.dist-info/RECORD
