Metadata-Version: 2.1
Name: alpha-galaxy
Version: 0.1.0
Summary: Alpha Galaxy is a framework of quantitative analysis development
License: MIT
Author: ZhengYu, Xu
Author-email: zen-xu@outlook.com
Requires-Python: >=3.7,<4.0
Classifier: License :: OSI Approved :: MIT License
Classifier: Programming Language :: Python :: 3
Classifier: Programming Language :: Python :: 3.7
Classifier: Programming Language :: Python :: 3.8
Classifier: Programming Language :: Python :: 3.9
